simcraft/__init__.py
simcraft/activities/__init__.py
simcraft/activities/activity.py
simcraft/activities/state_machine.py
simcraft/core/__init__.py
simcraft/core/clock.py
simcraft/core/entity.py
simcraft/core/event.py
simcraft/core/simulation.py
simcraft/examples/__init__.py
simcraft/examples/manufacturing.py
simcraft/examples/mm1_queue.py
simcraft/examples/port_terminal.py
simcraft/optimization/__init__.py
simcraft/optimization/base.py
simcraft/optimization/rl_interface.py
simcraft/random/__init__.py
simcraft/random/distributions.py
simcraft/random/streams.py
simcraft/resources/__init__.py
simcraft/resources/pool.py
simcraft/resources/queue.py
simcraft/resources/resource.py
simcraft/resources/server.py
simcraft/statistics/__init__.py
simcraft/statistics/counter.py
simcraft/statistics/monitor.py
simcraft/statistics/tally.py
simcraft/statistics/time_series.py
simcraft/utils/__init__.py
simcraft/utils/config.py
simcraft/utils/logging.py
simcraft/utils/visualization.py
simcraft-1.0.1.dist-info/licenses/LICENSE.txt
simcraft-1.0.1.dist-info/METADATA
simcraft-1.0.1.dist-info/WHEEL
simcraft-1.0.1.dist-info/top_level.txt
simcraft-1.0.1.dist-info/RECORD
