Metadata-Version: 2.4
Name: simcraft
Version: 1.0.1
Summary: A discrete event simulation framework for Python
Home-page: https://github.com/bulentsoykan/simcraft
Author: Bulent Soykan
Author-email: Bulent Soykan <soykanb@gmail.com>
License: MIT
Project-URL: Homepage, https://github.com/bulentsoykan/simcraft
Project-URL: Documentation, https://simcraft.readthedocs.io/
Project-URL: Repository, https://github.com/bulentsoykan/simcraft
Keywords: simulation,discrete-event,DES,modeling,optimization,reinforcement-learning
Classifier: Development Status :: 4 - Beta
Classifier: Intended Audience :: Developers
Classifier: Intended Audience :: Science/Research
Classifier: License :: OSI Approved :: MIT License
Classifier: Operating System :: OS Independent
Classifier: Programming Language :: Python :: 3
Classifier: Programming Language :: Python :: 3.8
Classifier: Programming Language :: Python :: 3.9
Classifier: Programming Language :: Python :: 3.10
Classifier: Programming Language :: Python :: 3.11
Classifier: Programming Language :: Python :: 3.12
Classifier: Topic :: Scientific/Engineering
Classifier: Topic :: Scientific/Engineering :: Artificial Intelligence
Requires-Python: >=3.8
License-File: LICENSE.txt
Requires-Dist: sortedcontainers>=2.4.0
Requires-Dist: numpy>=1.20.0
Provides-Extra: dev
Requires-Dist: pytest>=7.0.0; extra == "dev"
Requires-Dist: pytest-cov>=4.0.0; extra == "dev"
Requires-Dist: black>=23.0.0; extra == "dev"
Requires-Dist: mypy>=1.0.0; extra == "dev"
Provides-Extra: visualization
Requires-Dist: matplotlib>=3.5.0; extra == "visualization"
Requires-Dist: pandas>=1.4.0; extra == "visualization"
Provides-Extra: rl
Requires-Dist: torch>=2.0.0; extra == "rl"
Provides-Extra: all
Requires-Dist: matplotlib>=3.5.0; extra == "all"
Requires-Dist: pandas>=1.4.0; extra == "all"
Requires-Dist: torch>=2.0.0; extra == "all"
Requires-Dist: pyyaml>=6.0; extra == "all"
Provides-Extra: docs
Requires-Dist: sphinx>=7.0.0; extra == "docs"
Requires-Dist: sphinx-rtd-theme>=2.0.0; extra == "docs"
Requires-Dist: myst-parser>=2.0.0; extra == "docs"
Dynamic: author
Dynamic: home-page
Dynamic: license-file
Dynamic: requires-python
